alpheast/__init__.py
alpheast/engine.py
alpheast/config/__init__.py
alpheast/config/backtest_config.py
alpheast/config/config_loader.py
alpheast/config/data_source.py
alpheast/data/__init__.py
alpheast/data/alpha_vantage_price_bar_client.py
alpheast/data/price_bar_client.py
alpheast/events/__init__.py
alpheast/events/event.py
alpheast/events/event_enums.py
alpheast/events/event_queue.py
alpheast/handlers/__init__.py
alpheast/handlers/data_handler.py
alpheast/handlers/execution_handler.py
alpheast/handlers/simulated_execution_handler.py
alpheast/models/__init__.py
alpheast/models/backtest_results.py
alpheast/models/interval.py
alpheast/models/price_bar.py
alpheast/models/signal.py
alpheast/portfolio/__init__.py
alpheast/portfolio/benchmark_calculator.py
alpheast/portfolio/portfolio.py
alpheast/portfolio/portfolio_manager.py
alpheast/position_sizing/__init__.py
alpheast/position_sizing/base_position_sizing.py
alpheast/position_sizing/common/__init__.py
alpheast/position_sizing/common/fixed_allocation_sizing.py
alpheast/position_sizing/common/fixed_quantity_sizing.py
alpheast/shared/__init__.py
alpheast/shared/metrics.py
alpheast/shared/plotting.py
alpheast/shared/utils/project_root_finder.py
alpheast/strategy/__init__.py
alpheast/strategy/base_strategy.py
alpheast/strategy/common/__init__.py
alpheast/strategy/common/bollinger_bands_strategy.py
alpheast/strategy/common/buy_and_hold_strategy.py
alpheast/strategy/common/macd_strategy.py
alpheast/strategy/common/rsi_strategy.py
alpheast/strategy/common/sma_crossover_strategy.py
alpheast-0.1.3.dist-info/licenses/LICENSE.md
performance_tests/config.py
performance_tests/test_engine_performance.py
performance_tests/database/base_model.py
performance_tests/database/database.py
performance_tests/database/model.py
performance_tests/database/repository.py
tests/__init__.py
tests/config/test_config_loader.py
tests/handlers/test_data_handler.py
tests/portfolio/test_portfolio.py
tests/portfolio/test_portfolio_manager.py
alpheast-0.1.3.dist-info/METADATA
alpheast-0.1.3.dist-info/WHEEL
alpheast-0.1.3.dist-info/top_level.txt
alpheast-0.1.3.dist-info/RECORD
