Metadata-Version: 2.4
Name: alpheast
Version: 0.1.3
Summary: An event-driven backtesting engine for trading strategies.
Author-email: Tudor Andrei Orban <tudoraorban@protonmail.com>
License: MIT License
Project-URL: Documentation, https://alpheast.readthedocs.io/en/latest/
Project-URL: Homepage, https://github.com/TudorOrban/AlphEast
Project-URL: Issues, https://github.com/TudorOrban/AlphEast/issues
Project-URL: Changelog, https://github.com/TudorOrban/AlphEast/blob/main/CHANGELOG.md
Keywords: trading,backtesting,finance,event-driven,investment
Classifier: Programming Language :: Python :: 3
Classifier: Programming Language :: Python :: 3.8
Classifier: Programming Language :: Python :: 3.9
Classifier: Programming Language :: Python :: 3.10
Classifier: Programming Language :: Python :: 3.11
Classifier: License :: OSI Approved :: MIT License
Classifier: Operating System :: OS Independent
Classifier: Development Status :: 3 - Alpha
Classifier: Intended Audience :: Developers
Classifier: Intended Audience :: Financial and Insurance Industry
Classifier: Topic :: Office/Business :: Financial :: Investment
Requires-Python: >=3.8
License-File: LICENSE.md
Requires-Dist: requests
Requires-Dist: pandas
Requires-Dist: matplotlib
Dynamic: license-file
